Metadata-Version: 2.1
Name: package-gabriel-pereira
Version: 0.0.1
Summary: Teste para criar pacotes DIO.me
Home-page: https://github.com/gabbrielpereira/learningpython/package-gabriel-pereira
Author: Gabriel
Author-email: pereissgabriel@gmail.com
Requires-Python: >=3.8
Requires-Dist: aaaaa
